{"v":"5.5.6","fr":25,"ip":0,"op":61,"w":750,"h":1334,"nm":"reading","ddd":1,"assets":[],"fonts":{"list":[{"fName":"MF-SuBai-XinChao(Noncommercial)-Regular","ascent":84.082605689764}]},"layers":[{"ddd":1,"ind":1,"ty":4,"nm":"page 4","sr":1,"ks":{"o":{"a":0,"k":100,"ix":11},"rx":{"a":0,"k":0,"ix":8},"ry":{"a":1,"k":[{"i":{"x":[0.833],"y":[0.833]},"o":{"x":[0.167],"y":[0.167]},"t":36,"s":[0]},{"t":43,"s":[-180]}],"ix":9},"rz":{"a":0,"k":0,"ix":10},"or":{"a":0,"k":[0,0,0],"ix":7},"p":{"a":0,"k":[372.626,694.25,0.374],"ix":2},"a":{"a":0,"k":[-3.559,27.25,-0.467],"ix":1},"s":{"a":1,"k":[{"i":{"x":[0.833,0.833,0.833],"y":[0.833,0.833,0.833]},"o":{"x":[0.167,0.167,0.167],"y":[0.167,0.167,0.167]},"t":27,"s":[100,0,100]},{"t":36,"s":[100,100,100]}],"ix":6}},"ao":0,"shapes":[{"ty":"gr","it":[{"ind":0,"ty":"sh","ix":1,"ks":{"a":0,"k":{"i":[[0,0],[-39,-22]],"o":[[0,0],[39,22]],"v":[[-101,-87.5],[-18,-86]],"c":false},"ix":2},"nm":"路径 1","mn":"ADBE Vector Shape - Group","hd":false},{"ty":"st","c":{"a":0,"k":[0.98431372549,0.890196078431,0.690196078431,1],"ix":3},"o":{"a":0,"k":100,"ix":4},"w":{"a":0,"k":7,"ix":5},"lc":1,"lj":1,"ml":4,"bm":0,"nm":"描边 1","mn":"ADBE Vector Graphic - Stroke","hd":false},{"ty":"tr","p":{"a":0,"k":[-59.5,-93.5],"ix":2},"a":{"a":0,"k":[-59.5,-53.5],"ix":1},"s":{"a":0,"k":[100,100],"ix":3},"r":{"a":0,"k":0,"ix":6},"o":{"a":0,"k":100,"ix":7},"sk":{"a":0,"k":0,"ix":4},"sa":{"a":0,"k":0,"ix":5},"nm":"变换"}],"nm":"形状 3","np":3,"cix":2,"bm":0,"ix":1,"mn":"ADBE Vector Group","hd":false},{"ty":"gr","it":[{"ind":0,"ty":"sh","ix":1,"ks":{"a":0,"k":{"i":[[0,0],[-39,-22]],"o":[[0,0],[39,22]],"v":[[-101,-50],[-18,-48.5]],"c":false},"ix":2},"nm":"路径 1","mn":"ADBE Vector Shape - Group","hd":false},{"ty":"st","c":{"a":0,"k":[0.98431372549,0.890196078431,0.690196078431,1],"ix":3},"o":{"a":0,"k":100,"ix":4},"w":{"a":0,"k":7,"ix":5},"lc":1,"lj":1,"ml":4,"bm":0,"nm":"描边 1","mn":"ADBE Vector Graphic - Stroke","hd":false},{"ty":"tr","p":{"a":0,"k":[-59.5,-93.5],"ix":2},"a":{"a":0,"k":[-59.5,-53.5],"ix":1},"s":{"a":0,"k":[100,100],"ix":3},"r":{"a":0,"k":0,"ix":6},"o":{"a":0,"k":100,"ix":7},"sk":{"a":0,"k":0,"ix":4},"sa":{"a":0,"k":0,"ix":5},"nm":"变换"}],"nm":"形状 2","np":3,"cix":2,"bm":0,"ix":2,"mn":"ADBE Vector Group","hd":false},{"ty":"gr","it":[{"ind":0,"ty":"sh","ix":1,"ks":{"a":0,"k":{"i":[[0,0],[-39,-22]],"o":[[0,0],[39,22]],"v":[[-101,-50],[-18,-48.5]],"c":false},"ix":2},"nm":"路径 1","mn":"ADBE Vector Shape - Group","hd":false},{"ty":"st","c":{"a":0,"k":[0.98431372549,0.890196078431,0.690196078431,1],"ix":3},"o":{"a":0,"k":100,"ix":4},"w":{"a":0,"k":7,"ix":5},"lc":1,"lj":1,"ml":4,"bm":0,"nm":"描边 1","mn":"ADBE Vector Graphic - Stroke","hd":false},{"ty":"tr","p":{"a":0,"k":[-59.5,-53.5],"ix":2},"a":{"a":0,"k":[-59.5,-53.5],"ix":1},"s":{"a":0,"k":[100,100],"ix":3},"r":{"a":0,"k":0,"ix":6},"o":{"a":0,"k":100,"ix":7},"sk":{"a":0,"k":0,"ix":4},"sa":{"a":0,"k":0,"ix":5},"nm":"变换"}],"nm":"形状 1","np":3,"cix":2,"bm":0,"ix":3,"mn":"ADBE Vector Group","hd":false},{"ty":"gr","it":[{"ind":0,"ty":"sh","ix":1,"ks":{"a":0,"k":{"i":[[0,0],[11.046,0],[0,0],[0,11.046],[-15.187,-0.188],[-25.334,0.477]],"o":[[0,11.046],[0,0],[-11.046,0],[0,0],[7,0.086],[14.875,-0.28]],"v":[[57,87.75],[37,107.75],[-37,107.75],[-57,87.75],[-36.25,100],[36.25,100.405]],"c":true},"ix":2},"nm":"路径 1","mn":"ADBE Vector Shape - Group","hd":false},{"ty":"st","c":{"a":0,"k":[0.980391977348,0.882353001015,0.360783984614,1],"ix":3},"o":{"a":0,"k":100,"ix":4},"w":{"a":0,"k":0,"ix":5},"lc":1,"lj":1,"ml":4,"bm":0,"nm":"描边 1","mn":"ADBE Vector Graphic - Stroke","hd":false},{"ty":"fl","c":{"a":0,"k":[0.96862745098,0.796078431373,0.572549019608,1],"ix":4},"o":{"a":0,"k":100,"ix":5},"r":1,"bm":0,"nm":"填充 1","mn":"ADBE Vector Graphic - Fill","hd":false},{"ty":"tr","p":{"a":0,"k":[-58.5,-79.25],"ix":2},"a":{"a":0,"k":[0,0],"ix":1},"s":{"a":0,"k":[100,100],"ix":3},"r":{"a":0,"k":0,"ix":6},"o":{"a":0,"k":100,"ix":7},"sk":{"a":0,"k":0,"ix":4},"sa":{"a":0,"k":0,"ix":5},"nm":"变换"}],"nm":"矩形 2","np":3,"cix":2,"bm":0,"ix":4,"mn":"ADBE Vector Group","hd":false},{"ty":"gr","it":[{"ty":"rc","d":1,"s":{"a":0,"k":[114,215.5],"ix":2},"p":{"a":0,"k":[0,0],"ix":3},"r":{"a":0,"k":20,"ix":4},"nm":"矩形路径 1","mn":"ADBE Vector Shape - Rect","hd":false},{"ty":"st","c":{"a":0,"k":[0.980391977348,0.882353001015,0.360783984614,1],"ix":3},"o":{"a":0,"k":100,"ix":4},"w":{"a":0,"k":0,"ix":5},"lc":1,"lj":1,"ml":4,"bm":0,"nm":"描边 1","mn":"ADBE Vector Graphic - Stroke","hd":false},{"ty":"fl","c":{"a":1,"k":[{"i":{"x":[0.833],"y":[0.833]},"o":{"x":[0.167],"y":[0.167]},"t":38,"s":[0.988235294118,0.937254901961,0.81568627451,1]},{"t":41,"s":[0.984313726425,0.909803926945,0.729411780834,1]}],"ix":4},"o":{"a":0,"k":100,"ix":5},"r":1,"bm":0,"nm":"填充 1","mn":"ADBE Vector Graphic - Fill","hd":false},{"ty":"tr","p":{"a":0,"k":[-58.5,-79.25],"ix":2},"a":{"a":0,"k":[0,0],"ix":1},"s":{"a":0,"k":[100,100],"ix":3},"r":{"a":0,"k":0,"ix":6},"o":{"a":0,"k":100,"ix":7},"sk":{"a":0,"k":0,"ix":4},"sa":{"a":0,"k":0,"ix":5},"nm":"变换"}],"nm":"矩形 1","np":3,"cix":2,"bm":0,"ix":5,"mn":"ADBE Vector Group","hd":false}],"ip":27,"op":527,"st":27,"bm":0},{"ddd":1,"ind":2,"ty":4,"nm":"page 3","sr":1,"ks":{"o":{"a":0,"k":100,"ix":11},"rx":{"a":0,"k":0,"ix":8},"ry":{"a":1,"k":[{"i":{"x":[0.833],"y":[0.833]},"o":{"x":[0.167],"y":[0.167]},"t":28,"s":[0]},{"t":35,"s":[-180]}],"ix":9},"rz":{"a":0,"k":0,"ix":10},"or":{"a":0,"k":[0,0,0],"ix":7},"p":{"a":0,"k":[372.626,694.25,0.374],"ix":2},"a":{"a":0,"k":[-3.559,27.25,-0.467],"ix":1},"s":{"a":1,"k":[{"i":{"x":[0.833,0.833,0.833],"y":[0.833,0.833,0.833]},"o":{"x":[0.167,0.167,0.167],"y":[0.167,0.167,0.167]},"t":19,"s":[100,0,100]},{"t":28,"s":[100,100,100]}],"ix":6}},"ao":0,"shapes":[{"ty":"gr","it":[{"ind":0,"ty":"sh","ix":1,"ks":{"a":0,"k":{"i":[[0,0],[-39,-22]],"o":[[0,0],[39,22]],"v":[[-101,-87.5],[-18,-86]],"c":false},"ix":2},"nm":"路径 1","mn":"ADBE Vector Shape - Group","hd":false},{"ty":"st","c":{"a":0,"k":[0.98431372549,0.890196078431,0.690196078431,1],"ix":3},"o":{"a":0,"k":100,"ix":4},"w":{"a":0,"k":7,"ix":5},"lc":1,"lj":1,"ml":4,"bm":0,"nm":"描边 1","mn":"ADBE Vector Graphic - Stroke","hd":false},{"ty":"tr","p":{"a":0,"k":[-59.5,-93.5],"ix":2},"a":{"a":0,"k":[-59.5,-53.5],"ix":1},"s":{"a":0,"k":[100,100],"ix":3},"r":{"a":0,"k":0,"ix":6},"o":{"a":0,"k":100,"ix":7},"sk":{"a":0,"k":0,"ix":4},"sa":{"a":0,"k":0,"ix":5},"nm":"变换"}],"nm":"形状 3","np":3,"cix":2,"bm":0,"ix":1,"mn":"ADBE Vector Group","hd":false},{"ty":"gr","it":[{"ind":0,"ty":"sh","ix":1,"ks":{"a":0,"k":{"i":[[0,0],[-39,-22]],"o":[[0,0],[39,22]],"v":[[-101,-50],[-18,-48.5]],"c":false},"ix":2},"nm":"路径 1","mn":"ADBE Vector Shape - Group","hd":false},{"ty":"st","c":{"a":0,"k":[0.98431372549,0.890196078431,0.690196078431,1],"ix":3},"o":{"a":0,"k":100,"ix":4},"w":{"a":0,"k":7,"ix":5},"lc":1,"lj":1,"ml":4,"bm":0,"nm":"描边 1","mn":"ADBE Vector Graphic - Stroke","hd":false},{"ty":"tr","p":{"a":0,"k":[-59.5,-93.5],"ix":2},"a":{"a":0,"k":[-59.5,-53.5],"ix":1},"s":{"a":0,"k":[100,100],"ix":3},"r":{"a":0,"k":0,"ix":6},"o":{"a":0,"k":100,"ix":7},"sk":{"a":0,"k":0,"ix":4},"sa":{"a":0,"k":0,"ix":5},"nm":"变换"}],"nm":"形状 2","np":3,"cix":2,"bm":0,"ix":2,"mn":"ADBE Vector Group","hd":false},{"ty":"gr","it":[{"ind":0,"ty":"sh","ix":1,"ks":{"a":0,"k":{"i":[[0,0],[-39,-22]],"o":[[0,0],[39,22]],"v":[[-101,-50],[-18,-48.5]],"c":false},"ix":2},"nm":"路径 1","mn":"ADBE Vector Shape - Group","hd":false},{"ty":"st","c":{"a":0,"k":[0.98431372549,0.890196078431,0.690196078431,1],"ix":3},"o":{"a":0,"k":100,"ix":4},"w":{"a":0,"k":7,"ix":5},"lc":1,"lj":1,"ml":4,"bm":0,"nm":"描边 1","mn":"ADBE Vector Graphic - Stroke","hd":false},{"ty":"tr","p":{"a":0,"k":[-59.5,-53.5],"ix":2},"a":{"a":0,"k":[-59.5,-53.5],"ix":1},"s":{"a":0,"k":[100,100],"ix":3},"r":{"a":0,"k":0,"ix":6},"o":{"a":0,"k":100,"ix":7},"sk":{"a":0,"k":0,"ix":4},"sa":{"a":0,"k":0,"ix":5},"nm":"变换"}],"nm":"形状 1","np":3,"cix":2,"bm":0,"ix":3,"mn":"ADBE Vector Group","hd":false},{"ty":"gr","it":[{"ind":0,"ty":"sh","ix":1,"ks":{"a":0,"k":{"i":[[0,0],[11.046,0],[0,0],[0,11.046],[-15.187,-0.188],[-25.334,0.477]],"o":[[0,11.046],[0,0],[-11.046,0],[0,0],[7,0.086],[14.875,-0.28]],"v":[[57,87.75],[37,107.75],[-37,107.75],[-57,87.75],[-36.25,100],[36.25,100.405]],"c":true},"ix":2},"nm":"路径 1","mn":"ADBE Vector Shape - Group","hd":false},{"ty":"st","c":{"a":0,"k":[0.980391977348,0.882353001015,0.360783984614,1],"ix":3},"o":{"a":0,"k":100,"ix":4},"w":{"a":0,"k":0,"ix":5},"lc":1,"lj":1,"ml":4,"bm":0,"nm":"描边 1","mn":"ADBE Vector Graphic - Stroke","hd":false},{"ty":"fl","c":{"a":0,"k":[0.96862745098,0.796078431373,0.572549019608,1],"ix":4},"o":{"a":0,"k":100,"ix":5},"r":1,"bm":0,"nm":"填充 1","mn":"ADBE Vector Graphic - Fill","hd":false},{"ty":"tr","p":{"a":0,"k":[-58.5,-79.25],"ix":2},"a":{"a":0,"k":[0,0],"ix":1},"s":{"a":0,"k":[100,100],"ix":3},"r":{"a":0,"k":0,"ix":6},"o":{"a":0,"k":100,"ix":7},"sk":{"a":0,"k":0,"ix":4},"sa":{"a":0,"k":0,"ix":5},"nm":"变换"}],"nm":"矩形 2","np":3,"cix":2,"bm":0,"ix":4,"mn":"ADBE Vector Group","hd":false},{"ty":"gr","it":[{"ty":"rc","d":1,"s":{"a":0,"k":[114,215.5],"ix":2},"p":{"a":0,"k":[0,0],"ix":3},"r":{"a":0,"k":20,"ix":4},"nm":"矩形路径 1","mn":"ADBE Vector Shape - Rect","hd":false},{"ty":"st","c":{"a":0,"k":[0.980391977348,0.882353001015,0.360783984614,1],"ix":3},"o":{"a":0,"k":100,"ix":4},"w":{"a":0,"k":0,"ix":5},"lc":1,"lj":1,"ml":4,"bm":0,"nm":"描边 1","mn":"ADBE Vector Graphic - Stroke","hd":false},{"ty":"fl","c":{"a":1,"k":[{"i":{"x":[0.833],"y":[0.833]},"o":{"x":[0.167],"y":[0.167]},"t":30,"s":[0.988235294118,0.937254901961,0.81568627451,1]},{"t":33,"s":[0.984313726425,0.909803926945,0.729411780834,1]}],"ix":4},"o":{"a":0,"k":100,"ix":5},"r":1,"bm":0,"nm":"填充 1","mn":"ADBE Vector Graphic - Fill","hd":false},{"ty":"tr","p":{"a":0,"k":[-58.5,-79.25],"ix":2},"a":{"a":0,"k":[0,0],"ix":1},"s":{"a":0,"k":[100,100],"ix":3},"r":{"a":0,"k":0,"ix":6},"o":{"a":0,"k":100,"ix":7},"sk":{"a":0,"k":0,"ix":4},"sa":{"a":0,"k":0,"ix":5},"nm":"变换"}],"nm":"矩形 1","np":3,"cix":2,"bm":0,"ix":5,"mn":"ADBE Vector Group","hd":false}],"ip":19,"op":519,"st":19,"bm":0},{"ddd":1,"ind":3,"ty":4,"nm":"page 2","sr":1,"ks":{"o":{"a":0,"k":100,"ix":11},"rx":{"a":0,"k":0,"ix":8},"ry":{"a":1,"k":[{"i":{"x":[0.833],"y":[0.833]},"o":{"x":[0.167],"y":[0.167]},"t":22,"s":[0]},{"t":29,"s":[-180]}],"ix":9},"rz":{"a":0,"k":0,"ix":10},"or":{"a":0,"k":[0,0,0],"ix":7},"p":{"a":0,"k":[371.626,694.25,0.374],"ix":2},"a":{"a":0,"k":[-3.559,27.25,-0.467],"ix":1},"s":{"a":1,"k":[{"i":{"x":[0.833,0.833,0.833],"y":[0.833,0.833,0.833]},"o":{"x":[0.167,0.167,0.167],"y":[0.167,0.167,0.167]},"t":13,"s":[100,0,100]},{"t":22,"s":[100,100,100]}],"ix":6}},"ao":0,"shapes":[{"ty":"gr","it":[{"ind":0,"ty":"sh","ix":1,"ks":{"a":0,"k":{"i":[[0,0],[-39,-22]],"o":[[0,0],[39,22]],"v":[[-101,-87.5],[-18,-86]],"c":false},"ix":2},"nm":"路径 1","mn":"ADBE Vector Shape - Group","hd":false},{"ty":"st","c":{"a":0,"k":[0.98431372549,0.890196078431,0.690196078431,1],"ix":3},"o":{"a":0,"k":100,"ix":4},"w":{"a":0,"k":7,"ix":5},"lc":1,"lj":1,"ml":4,"bm":0,"nm":"描边 1","mn":"ADBE Vector Graphic - Stroke","hd":false},{"ty":"tr","p":{"a":0,"k":[-59.5,-93.5],"ix":2},"a":{"a":0,"k":[-59.5,-53.5],"ix":1},"s":{"a":0,"k":[100,100],"ix":3},"r":{"a":0,"k":0,"ix":6},"o":{"a":0,"k":100,"ix":7},"sk":{"a":0,"k":0,"ix":4},"sa":{"a":0,"k":0,"ix":5},"nm":"变换"}],"nm":"形状 3","np":3,"cix":2,"bm":0,"ix":1,"mn":"ADBE Vector Group","hd":false},{"ty":"gr","it":[{"ind":0,"ty":"sh","ix":1,"ks":{"a":0,"k":{"i":[[0,0],[-39,-22]],"o":[[0,0],[39,22]],"v":[[-101,-50],[-18,-48.5]],"c":false},"ix":2},"nm":"路径 1","mn":"ADBE Vector Shape - Group","hd":false},{"ty":"st","c":{"a":0,"k":[0.98431372549,0.890196078431,0.690196078431,1],"ix":3},"o":{"a":0,"k":100,"ix":4},"w":{"a":0,"k":7,"ix":5},"lc":1,"lj":1,"ml":4,"bm":0,"nm":"描边 1","mn":"ADBE Vector Graphic - Stroke","hd":false},{"ty":"tr","p":{"a":0,"k":[-59.5,-93.5],"ix":2},"a":{"a":0,"k":[-59.5,-53.5],"ix":1},"s":{"a":0,"k":[100,100],"ix":3},"r":{"a":0,"k":0,"ix":6},"o":{"a":0,"k":100,"ix":7},"sk":{"a":0,"k":0,"ix":4},"sa":{"a":0,"k":0,"ix":5},"nm":"变换"}],"nm":"形状 2","np":3,"cix":2,"bm":0,"ix":2,"mn":"ADBE Vector Group","hd":false},{"ty":"gr","it":[{"ind":0,"ty":"sh","ix":1,"ks":{"a":0,"k":{"i":[[0,0],[-39,-22]],"o":[[0,0],[39,22]],"v":[[-101,-50],[-18,-48.5]],"c":false},"ix":2},"nm":"路径 1","mn":"ADBE Vector Shape - Group","hd":false},{"ty":"st","c":{"a":0,"k":[0.98431372549,0.890196078431,0.690196078431,1],"ix":3},"o":{"a":0,"k":100,"ix":4},"w":{"a":0,"k":7,"ix":5},"lc":1,"lj":1,"ml":4,"bm":0,"nm":"描边 1","mn":"ADBE Vector Graphic - Stroke","hd":false},{"ty":"tr","p":{"a":0,"k":[-59.5,-53.5],"ix":2},"a":{"a":0,"k":[-59.5,-53.5],"ix":1},"s":{"a":0,"k":[100,100],"ix":3},"r":{"a":0,"k":0,"ix":6},"o":{"a":0,"k":100,"ix":7},"sk":{"a":0,"k":0,"ix":4},"sa":{"a":0,"k":0,"ix":5},"nm":"变换"}],"nm":"形状 1","np":3,"cix":2,"bm":0,"ix":3,"mn":"ADBE Vector Group","hd":false},{"ty":"gr","it":[{"ind":0,"ty":"sh","ix":1,"ks":{"a":0,"k":{"i":[[0,0],[11.046,0],[0,0],[0,11.046],[-15.187,-0.188],[-25.334,0.477]],"o":[[0,11.046],[0,0],[-11.046,0],[0,0],[7,0.086],[14.875,-0.28]],"v":[[57,87.75],[37,107.75],[-37,107.75],[-57,87.75],[-36.25,100],[36.25,100.405]],"c":true},"ix":2},"nm":"路径 1","mn":"ADBE Vector Shape - Group","hd":false},{"ty":"st","c":{"a":0,"k":[0.980391977348,0.882353001015,0.360783984614,1],"ix":3},"o":{"a":0,"k":100,"ix":4},"w":{"a":0,"k":0,"ix":5},"lc":1,"lj":1,"ml":4,"bm":0,"nm":"描边 1","mn":"ADBE Vector Graphic - Stroke","hd":false},{"ty":"fl","c":{"a":0,"k":[0.96862745098,0.796078431373,0.572549019608,1],"ix":4},"o":{"a":0,"k":100,"ix":5},"r":1,"bm":0,"nm":"填充 1","mn":"ADBE Vector Graphic - Fill","hd":false},{"ty":"tr","p":{"a":0,"k":[-58.5,-79.25],"ix":2},"a":{"a":0,"k":[0,0],"ix":1},"s":{"a":0,"k":[100,100],"ix":3},"r":{"a":0,"k":0,"ix":6},"o":{"a":0,"k":100,"ix":7},"sk":{"a":0,"k":0,"ix":4},"sa":{"a":0,"k":0,"ix":5},"nm":"变换"}],"nm":"矩形 2","np":3,"cix":2,"bm":0,"ix":4,"mn":"ADBE Vector Group","hd":false},{"ty":"gr","it":[{"ty":"rc","d":1,"s":{"a":0,"k":[114,215.5],"ix":2},"p":{"a":0,"k":[0,0],"ix":3},"r":{"a":0,"k":20,"ix":4},"nm":"矩形路径 1","mn":"ADBE Vector Shape - Rect","hd":false},{"ty":"st","c":{"a":0,"k":[0.980391977348,0.882353001015,0.360783984614,1],"ix":3},"o":{"a":0,"k":100,"ix":4},"w":{"a":0,"k":0,"ix":5},"lc":1,"lj":1,"ml":4,"bm":0,"nm":"描边 1","mn":"ADBE Vector Graphic - Stroke","hd":false},{"ty":"fl","c":{"a":1,"k":[{"i":{"x":[0.833],"y":[0.833]},"o":{"x":[0.167],"y":[0.167]},"t":24,"s":[0.988235294118,0.937254901961,0.81568627451,1]},{"t":27,"s":[0.984313726425,0.909803926945,0.729411780834,1]}],"ix":4},"o":{"a":0,"k":100,"ix":5},"r":1,"bm":0,"nm":"填充 1","mn":"ADBE Vector Graphic - Fill","hd":false},{"ty":"tr","p":{"a":0,"k":[-58.5,-79.25],"ix":2},"a":{"a":0,"k":[0,0],"ix":1},"s":{"a":0,"k":[100,100],"ix":3},"r":{"a":0,"k":0,"ix":6},"o":{"a":0,"k":100,"ix":7},"sk":{"a":0,"k":0,"ix":4},"sa":{"a":0,"k":0,"ix":5},"nm":"变换"}],"nm":"矩形 1","np":3,"cix":2,"bm":0,"ix":5,"mn":"ADBE Vector Group","hd":false}],"ip":13,"op":513,"st":13,"bm":0},{"ddd":1,"ind":4,"ty":4,"nm":"page","sr":1,"ks":{"o":{"a":0,"k":100,"ix":11},"rx":{"a":0,"k":0,"ix":8},"ry":{"a":0,"k":0,"ix":9},"rz":{"a":0,"k":0,"ix":10},"or":{"a":0,"k":[0,0,0],"ix":7},"p":{"a":0,"k":[373.187,695.125,0.374],"ix":2},"a":{"a":0,"k":[-1.813,28.125,0.374],"ix":1},"s":{"a":1,"k":[{"i":{"x":[0.833,0.833,0.833],"y":[0.833,0.833,0.833]},"o":{"x":[0.167,0.167,0.167],"y":[0.167,0.167,0.167]},"t":13,"s":[100,0,100]},{"t":22,"s":[100,100,100]}],"ix":6}},"ao":0,"shapes":[{"ty":"gr","it":[{"ind":0,"ty":"sh","ix":1,"ks":{"a":0,"k":{"i":[[0,0],[-39,-22]],"o":[[0,0],[39,22]],"v":[[-101,-87.5],[-18,-86]],"c":false},"ix":2},"nm":"路径 1","mn":"ADBE Vector Shape - Group","hd":false},{"ty":"st","c":{"a":0,"k":[1,0.909243714576,0.717647058824,1],"ix":3},"o":{"a":0,"k":100,"ix":4},"w":{"a":0,"k":7,"ix":5},"lc":1,"lj":1,"ml":4,"bm":0,"nm":"描边 1","mn":"ADBE Vector Graphic - Stroke","hd":false},{"ty":"tr","p":{"a":0,"k":[-59.5,-93.5],"ix":2},"a":{"a":0,"k":[-59.5,-53.5],"ix":1},"s":{"a":0,"k":[100,100],"ix":3},"r":{"a":0,"k":0,"ix":6},"o":{"a":0,"k":100,"ix":7},"sk":{"a":0,"k":0,"ix":4},"sa":{"a":0,"k":0,"ix":5},"nm":"变换"}],"nm":"形状 3","np":3,"cix":2,"bm":0,"ix":1,"mn":"ADBE Vector Group","hd":false},{"ty":"gr","it":[{"ind":0,"ty":"sh","ix":1,"ks":{"a":0,"k":{"i":[[0,0],[-39,-22]],"o":[[0,0],[39,22]],"v":[[-101,-50],[-18,-48.5]],"c":false},"ix":2},"nm":"路径 1","mn":"ADBE Vector Shape - Group","hd":false},{"ty":"st","c":{"a":0,"k":[1,0.909243714576,0.717647058824,1],"ix":3},"o":{"a":0,"k":100,"ix":4},"w":{"a":0,"k":7,"ix":5},"lc":1,"lj":1,"ml":4,"bm":0,"nm":"描边 1","mn":"ADBE Vector Graphic - Stroke","hd":false},{"ty":"tr","p":{"a":0,"k":[-59.5,-93.5],"ix":2},"a":{"a":0,"k":[-59.5,-53.5],"ix":1},"s":{"a":0,"k":[100,100],"ix":3},"r":{"a":0,"k":0,"ix":6},"o":{"a":0,"k":100,"ix":7},"sk":{"a":0,"k":0,"ix":4},"sa":{"a":0,"k":0,"ix":5},"nm":"变换"}],"nm":"形状 2","np":3,"cix":2,"bm":0,"ix":2,"mn":"ADBE Vector Group","hd":false},{"ty":"gr","it":[{"ind":0,"ty":"sh","ix":1,"ks":{"a":0,"k":{"i":[[0,0],[-39,-22]],"o":[[0,0],[39,22]],"v":[[-101,-50],[-18,-48.5]],"c":false},"ix":2},"nm":"路径 1","mn":"ADBE Vector Shape - Group","hd":false},{"ty":"st","c":{"a":0,"k":[1,0.909243714576,0.717647058824,1],"ix":3},"o":{"a":0,"k":100,"ix":4},"w":{"a":0,"k":7,"ix":5},"lc":1,"lj":1,"ml":4,"bm":0,"nm":"描边 1","mn":"ADBE Vector Graphic - Stroke","hd":false},{"ty":"tr","p":{"a":0,"k":[-59.5,-53.5],"ix":2},"a":{"a":0,"k":[-59.5,-53.5],"ix":1},"s":{"a":0,"k":[100,100],"ix":3},"r":{"a":0,"k":0,"ix":6},"o":{"a":0,"k":100,"ix":7},"sk":{"a":0,"k":0,"ix":4},"sa":{"a":0,"k":0,"ix":5},"nm":"变换"}],"nm":"形状 1","np":3,"cix":2,"bm":0,"ix":3,"mn":"ADBE Vector Group","hd":false},{"ty":"gr","it":[{"ind":0,"ty":"sh","ix":1,"ks":{"a":0,"k":{"i":[[0,0],[11.046,0],[0,0],[0,11.046],[-15.187,-0.188],[-25.334,0.477]],"o":[[0,11.046],[0,0],[-11.046,0],[0,0],[7,0.086],[14.875,-0.28]],"v":[[57,87.75],[37,107.75],[-37,107.75],[-57,87.75],[-36.25,100],[36.25,100.405]],"c":true},"ix":2},"nm":"路径 1","mn":"ADBE Vector Shape - Group","hd":false},{"ty":"st","c":{"a":0,"k":[0.980391977348,0.882353001015,0.360783984614,1],"ix":3},"o":{"a":0,"k":100,"ix":4},"w":{"a":0,"k":0,"ix":5},"lc":1,"lj":1,"ml":4,"bm":0,"nm":"描边 1","mn":"ADBE Vector Graphic - Stroke","hd":false},{"ty":"fl","c":{"a":0,"k":[0.96862745098,0.796078431373,0.572549019608,1],"ix":4},"o":{"a":0,"k":100,"ix":5},"r":1,"bm":0,"nm":"填充 1","mn":"ADBE Vector Graphic - Fill","hd":false},{"ty":"tr","p":{"a":0,"k":[-58.5,-79.25],"ix":2},"a":{"a":0,"k":[0,0],"ix":1},"s":{"a":0,"k":[100,100],"ix":3},"r":{"a":0,"k":0,"ix":6},"o":{"a":0,"k":100,"ix":7},"sk":{"a":0,"k":0,"ix":4},"sa":{"a":0,"k":0,"ix":5},"nm":"变换"}],"nm":"矩形 2","np":3,"cix":2,"bm":0,"ix":4,"mn":"ADBE Vector Group","hd":false},{"ty":"gr","it":[{"ty":"rc","d":1,"s":{"a":0,"k":[114,215.5],"ix":2},"p":{"a":0,"k":[0,0],"ix":3},"r":{"a":0,"k":20,"ix":4},"nm":"矩形路径 1","mn":"ADBE Vector Shape - Rect","hd":false},{"ty":"st","c":{"a":0,"k":[0.980391977348,0.882353001015,0.360783984614,1],"ix":3},"o":{"a":0,"k":100,"ix":4},"w":{"a":0,"k":0,"ix":5},"lc":1,"lj":1,"ml":4,"bm":0,"nm":"描边 1","mn":"ADBE Vector Graphic - Stroke","hd":false},{"ty":"fl","c":{"a":0,"k":[0.988235294118,0.937254901961,0.81568627451,1],"ix":4},"o":{"a":0,"k":100,"ix":5},"r":1,"bm":0,"nm":"填充 1","mn":"ADBE Vector Graphic - Fill","hd":false},{"ty":"tr","p":{"a":0,"k":[-58.5,-79.25],"ix":2},"a":{"a":0,"k":[0,0],"ix":1},"s":{"a":0,"k":[100,100],"ix":3},"r":{"a":0,"k":0,"ix":6},"o":{"a":0,"k":100,"ix":7},"sk":{"a":0,"k":0,"ix":4},"sa":{"a":0,"k":0,"ix":5},"nm":"变换"}],"nm":"矩形 1","np":3,"cix":2,"bm":0,"ix":5,"mn":"ADBE Vector Group","hd":false}],"ip":13,"op":513,"st":13,"bm":0},{"ddd":1,"ind":5,"ty":4,"nm":"book 2","sr":1,"ks":{"o":{"a":0,"k":100,"ix":11},"rx":{"a":0,"k":0,"ix":8},"ry":{"a":1,"k":[{"i":{"x":[0.833],"y":[0.833]},"o":{"x":[0.167],"y":[0.167]},"t":8,"s":[0]},{"t":16,"s":[-180]}],"ix":9},"rz":{"a":0,"k":0,"ix":10},"or":{"a":0,"k":[0,0,0],"ix":7},"p":{"a":0,"k":[369.938,710.563,0],"ix":2},"a":{"a":0,"k":[-0.938,41.563,0],"ix":1},"s":{"a":1,"k":[{"i":{"x":[0.833,0.833,0.833],"y":[0.833,0.833,0.833]},"o":{"x":[0.167,0.167,0.167],"y":[0.167,0.167,0.167]},"t":0,"s":[100,100,100]},{"t":8,"s":[100,100,100]}],"ix":6}},"ao":0,"hasMask":true,"masksProperties":[{"inv":false,"mode":"a","pt":{"a":1,"k":[{"i":{"x":0.833,"y":0.833},"o":{"x":0.167,"y":0.167},"t":0,"s":[{"i":[[11.046,0],[0,0],[0,-11.046],[0,0],[-11.046,0],[0,0],[0,11.046],[0,0]],"o":[[0,0],[-11.046,0],[0,0],[0,11.046],[0,0],[11.046,0],[0,0],[0,-11.046]],"v":[[-14.5,44],[-115.5,44],[-135.5,64],[-135.5,69],[-115.5,89],[-14.5,89],[5.5,69],[5.5,64]],"c":true}]},{"i":{"x":0.833,"y":0.833},"o":{"x":0.167,"y":0.167},"t":5,"s":[{"i":[[11.046,0],[0,0],[0,-11.046],[0,0],[-11.046,0],[0,0],[0,11.046],[0,0]],"o":[[0,0],[-11.046,0],[0,0],[0,11.046],[0,0],[11.046,0],[0,0],[0,-11.046]],"v":[[-20.5,-88.5],[-111.625,-88.5],[-131.625,-68.5],[-131.625,69],[-111.625,89],[-20.5,89],[-0.5,69],[-0.5,-68.5]],"c":true}]},{"t":8,"s":[{"i":[[11.046,0],[0,0],[0,-11.046],[0,0],[-11.046,0],[0,0],[0,11.046],[0,0]],"o":[[0,0],[-11.046,0],[0,0],[0,11.046],[0,0],[11.046,0],[0,0],[0,-11.046]],"v":[[-14.5,-168],[-115.5,-168],[-135.5,-148],[-135.5,69],[-115.5,89],[-14.5,89],[5.5,69],[5.5,-148]],"c":true}]}],"ix":1},"o":{"a":0,"k":100,"ix":3},"x":{"a":0,"k":0,"ix":4},"nm":"蒙版 1"}],"shapes":[{"ty":"gr","it":[{"ind":0,"ty":"sh","ix":1,"ks":{"a":0,"k":{"i":[[0,-11.046],[0,0],[11.046,0],[0,0],[-0.25,18],[0,0],[-11.046,0],[0,0]],"o":[[0,0],[0,11.046],[0,0],[-16.75,0.5],[0,0],[0.75,-17.5],[0,0],[11.046,0]],"v":[[64.5,-88],[64.5,84],[50.25,101.5],[-39,101.5],[-66.5,71.5],[-66.5,-76],[-46.25,-104],[47.5,-104]],"c":true},"ix":2},"nm":"路径 1","mn":"ADBE Vector Shape - Group","hd":false},{"ty":"st","c":{"a":0,"k":[0.980391977348,0.882353001015,0.360783984614,1],"ix":3},"o":{"a":0,"k":100,"ix":4},"w":{"a":0,"k":0,"ix":5},"lc":1,"lj":1,"ml":4,"bm":0,"nm":"描边 1","mn":"ADBE Vector Graphic - Stroke","hd":false},{"ty":"fl","c":{"a":1,"k":[{"i":{"x":[0.833],"y":[0.833]},"o":{"x":[0.167],"y":[0.167]},"t":10,"s":[0.419607843137,0.176470588235,0.925490196078,1]},{"i":{"x":[0.833],"y":[0.833]},"o":{"x":[0.167],"y":[0.167]},"t":12,"s":[0.390418678522,0.157754704356,0.874509811401,1]},{"i":{"x":[0.833],"y":[0.833]},"o":{"x":[0.167],"y":[0.167]},"t":16,"s":[0.390418678522,0.157754704356,0.874509811401,1]},{"t":18,"s":[0.419607843137,0.176470588235,0.925490196078,1]}],"ix":4},"o":{"a":0,"k":100,"ix":5},"r":1,"bm":0,"nm":"填充 1","mn":"ADBE Vector Graphic - Fill","hd":false},{"ty":"tr","p":{"a":0,"k":[-65.25,-59.5],"ix":2},"a":{"a":0,"k":[0,0],"ix":1},"s":{"a":0,"k":[100,100],"ix":3},"r":{"a":0,"k":0,"ix":6},"o":{"a":0,"k":100,"ix":7},"sk":{"a":0,"k":0,"ix":4},"sa":{"a":0,"k":0,"ix":5},"nm":"变换"}],"nm":"矩形 1","np":3,"cix":2,"bm":0,"ix":1,"mn":"ADBE Vector Group","hd":false}],"ip":0,"op":500,"st":0,"bm":0},{"ddd":1,"ind":6,"ty":4,"nm":"book","sr":1,"ks":{"o":{"a":0,"k":100,"ix":11},"rx":{"a":0,"k":0,"ix":8},"ry":{"a":0,"k":0,"ix":9},"rz":{"a":0,"k":0,"ix":10},"or":{"a":0,"k":[0,0,0],"ix":7},"p":{"a":0,"k":[371.5,709.5,0],"ix":2},"a":{"a":0,"k":[-2.5,40.5,0],"ix":1},"s":{"a":1,"k":[{"i":{"x":[0.833,0.833,0.833],"y":[0.833,0.833,0.833]},"o":{"x":[0.167,0.167,0.167],"y":[0.167,0.167,0.167]},"t":0,"s":[100,100,100]},{"t":8,"s":[100,100,100]}],"ix":6}},"ao":0,"hasMask":true,"masksProperties":[{"inv":false,"mode":"a","pt":{"a":1,"k":[{"i":{"x":0.833,"y":0.833},"o":{"x":0.167,"y":0.167},"t":0,"s":[{"i":[[11.046,0],[0,0],[0,-11.046],[0,0],[-11.046,0],[0,0],[0,11.046],[0,0]],"o":[[0,0],[-11.046,0],[0,0],[0,11.046],[0,0],[11.046,0],[0,0],[0,-11.046]],"v":[[-14.5,44],[-115.5,44],[-135.5,64],[-135.5,69],[-115.5,89],[-14.5,89],[5.5,69],[5.5,64]],"c":true}]},{"i":{"x":0.833,"y":0.833},"o":{"x":0.167,"y":0.167},"t":5,"s":[{"i":[[11.046,0],[0,0],[0,-11.046],[0,0],[-11.046,0],[0,0],[0,11.046],[0,0]],"o":[[0,0],[-11.046,0],[0,0],[0,11.046],[0,0],[11.046,0],[0,0],[0,-11.046]],"v":[[-20.5,-88.5],[-111.625,-88.5],[-131.625,-68.5],[-131.625,69],[-111.625,89],[-20.5,89],[-0.5,69],[-0.5,-68.5]],"c":true}]},{"t":8,"s":[{"i":[[11.046,0],[0,0],[0,-11.046],[0,0],[-11.046,0],[0,0],[0,11.046],[0,0]],"o":[[0,0],[-11.046,0],[0,0],[0,11.046],[0,0],[11.046,0],[0,0],[0,-11.046]],"v":[[-14.5,-168],[-115.5,-168],[-135.5,-148],[-135.5,69],[-115.5,89],[-14.5,89],[5.5,69],[5.5,-148]],"c":true}]}],"ix":1},"o":{"a":0,"k":100,"ix":3},"x":{"a":0,"k":0,"ix":4},"nm":"蒙版 1"}],"shapes":[{"ty":"gr","it":[{"ind":0,"ty":"sh","ix":1,"ks":{"a":0,"k":{"i":[[0,-11.046],[0,0],[11.046,0],[0,0],[-0.25,18],[0,0],[-11.046,0],[0,0]],"o":[[0,0],[0,11.046],[0,0],[-16.75,0.5],[0,0],[0.75,-17.5],[0,0],[11.046,0]],"v":[[64.5,-88],[64.5,84],[50.25,101.5],[-39,101.5],[-66.5,71.5],[-66.5,-76],[-46.25,-104],[47.5,-104]],"c":true},"ix":2},"nm":"路径 1","mn":"ADBE Vector Shape - Group","hd":false},{"ty":"st","c":{"a":0,"k":[0.980391977348,0.882353001015,0.360783984614,1],"ix":3},"o":{"a":0,"k":100,"ix":4},"w":{"a":0,"k":0,"ix":5},"lc":1,"lj":1,"ml":4,"bm":0,"nm":"描边 1","mn":"ADBE Vector Graphic - Stroke","hd":false},{"ty":"fl","c":{"a":0,"k":[0.419607843137,0.176470588235,0.925490196078,1],"ix":4},"o":{"a":0,"k":100,"ix":5},"r":1,"bm":0,"nm":"填充 1","mn":"ADBE Vector Graphic - Fill","hd":false},{"ty":"tr","p":{"a":0,"k":[-65.25,-59.5],"ix":2},"a":{"a":0,"k":[0,0],"ix":1},"s":{"a":0,"k":[100,100],"ix":3},"r":{"a":0,"k":0,"ix":6},"o":{"a":0,"k":100,"ix":7},"sk":{"a":0,"k":0,"ix":4},"sa":{"a":0,"k":0,"ix":5},"nm":"变换"}],"nm":"矩形 1","np":3,"cix":2,"bm":0,"ix":1,"mn":"ADBE Vector Group","hd":false}],"ip":0,"op":500,"st":0,"bm":0},{"ddd":1,"ind":7,"ty":5,"nm":"真题阅读","sr":1,"ks":{"o":{"a":0,"k":100,"ix":11},"rx":{"a":0,"k":0,"ix":8},"ry":{"a":0,"k":0,"ix":9},"rz":{"a":0,"k":0,"ix":10},"or":{"a":1,"k":[{"i":{"x":0.667,"y":1},"o":{"x":0.333,"y":0},"t":35,"s":[81,0,0],"to":[0,0,0],"ti":[0,0,0]},{"i":{"x":0.667,"y":1},"o":{"x":0.333,"y":0},"t":42,"s":[298,0,0],"to":[0,0,0],"ti":[0,0,0]},{"i":{"x":0.667,"y":1},"o":{"x":0.333,"y":0},"t":46,"s":[45,0,0],"to":[0,0,0],"ti":[0,0,0]},{"i":{"x":0.667,"y":1},"o":{"x":0.333,"y":0},"t":49,"s":[327,0,0],"to":[0,0,0],"ti":[0,0,0]},{"i":{"x":0.833,"y":1},"o":{"x":0.167,"y":0},"t":51,"s":[16,0,0],"to":[0,0,0],"ti":[0,0,0]},{"t":52,"s":[0,0,0]}],"ix":7},"p":{"a":0,"k":[372,806,0],"ix":2},"a":{"a":0,"k":[200,-35.199,3.985],"ix":1},"s":{"a":0,"k":[100,100,100],"ix":6}},"ao":0,"t":{"d":{"k":[{"s":{"s":100,"f":"MF-SuBai-XinChao(Noncommercial)-Regular","t":"真题阅读","j":0,"tr":0,"lh":120,"ls":0,"fc":[1,1,1]},"t":0}]},"p":{},"m":{"g":1,"a":{"a":0,"k":[0,0],"ix":2}},"a":[]},"ip":35,"op":508,"st":8,"bm":0}],"markers":[],"chars":[{"ch":"真","size":100,"w":100,"data":{"shapes":[{"ty":"gr","it":[{"ind":0,"ty":"sh","ix":1,"ks":{"a":0,"k":{"i":[[0,0],[-0.2,1.466],[0.866,1.066],[0,0],[-0.167,-1.634],[-1.934,-1.134],[0,0],[-1.7,0.066],[-1.167,0.866],[-0.634,1.366],[0.1,1.366],[0.866,1.133],[1.733,0.333],[0,0],[0,0],[-0.8,0.834],[0,1.134],[0.833,0.834],[1.2,-0.066],[0,0],[0.633,0.667],[0,1.667],[0,0],[1.033,1.367],[1.5,0.734],[1.8,0.1],[1.5,-0.7],[1.033,-1.466],[0,-2.333],[0,0],[-0.5,-1.066],[-0.8,-0.8],[-1.067,-0.433],[-1.2,0],[0,0],[0,0],[0.866,-1.1],[0.1,-1.367],[-0.6,-1.367],[-1.2,-0.867],[-1.7,-0.067],[-2.067,1.2]],"o":[[1.933,-1.134],[0.2,-1.467],[0,0],[-1.067,1.067],[0.166,1.633],[0,0],[2.066,1.2],[1.7,-0.067],[1.166,-0.867],[0.633,-1.367],[-0.1,-1.367],[-0.867,-1.134],[0,0],[0,0],[1.2,0],[0.8,-0.833],[-0.067,-1.2],[-0.834,-0.833],[0,0],[-1.2,0.067],[-0.634,-0.666],[0,0],[0,-1.933],[-1.034,-1.366],[-1.5,-0.733],[-1.8,-0.1],[-1.5,0.7],[-1.034,1.467],[0,0],[0,1.267],[0.5,1.067],[0.8,0.8],[1.066,0.434],[0,0],[0,0],[-1.734,0.4],[-0.867,1.1],[-0.1,1.366],[0.6,1.366],[1.2,0.866],[1.7,0.066],[0,0]],"v":[[37.7,7],[40.9,3.1],[39.9,-0.7],[60.6,-1.2],[59.25,2.85],[62.4,7],[76.6,14.5],[82.25,16.2],[86.55,14.8],[89.25,11.45],[90.05,7.35],[88.6,3.6],[84.7,1.4],[71.7,-1.4],[87.7,-1.7],[90.7,-2.95],[91.9,-5.9],[90.55,-8.95],[87.5,-10.1],[32.3,-9.2],[29.55,-10.1],[28.6,-13.6],[28.6,-35.7],[27.05,-40.65],[23.25,-43.8],[18.3,-45.05],[13.35,-44.15],[9.55,-40.9],[8,-35.2],[8,-9],[8.75,-5.5],[10.7,-2.7],[13.5,-0.85],[16.9,-0.2],[23.9,-0.4],[15.5,1.4],[11.6,3.65],[10.15,7.35],[10.9,11.45],[13.6,14.8],[17.95,16.2],[23.6,14.5]],"c":true},"ix":2},"nm":"真","mn":"ADBE Vector Shape - Group","hd":false},{"ind":1,"ty":"sh","ix":2,"ks":{"a":0,"k":{"i":[[0,0],[-1.2,0.534],[-0.9,0.9],[-0.534,1.2],[0,1.4],[0,0],[0.533,1.2],[0.9,0.9],[1.2,0.5],[1.4,0],[0,0],[1.2,-0.533],[0.9,-0.9],[0.533,-1.233],[0,-1.4],[0,0],[-0.534,-1.233],[-0.9,-0.9],[-1.2,-0.533],[-1.4,0]],"o":[[1.4,0],[1.2,-0.533],[0.9,-0.9],[0.533,-1.2],[0,0],[0,-1.4],[-0.534,-1.2],[-0.9,-0.9],[-1.2,-0.5],[0,0],[-1.4,0],[-1.2,0.534],[-0.9,0.9],[-0.534,1.234],[0,0],[0,1.4],[0.533,1.234],[0.9,0.9],[1.2,0.534],[0,0]],"v":[[77.5,-13.2],[81.4,-14],[84.55,-16.15],[86.7,-19.3],[87.5,-23.2],[87.5,-41.8],[86.7,-45.7],[84.55,-48.85],[81.4,-50.95],[77.5,-51.7],[42,-51.1],[38.1,-50.3],[34.95,-48.15],[32.8,-44.95],[32,-41],[32,-22.5],[32.8,-18.55],[34.95,-15.35],[38.1,-13.2],[42,-12.4]],"c":true},"ix":2},"nm":"真","mn":"ADBE Vector Shape - Group","hd":false},{"ind":2,"ty":"sh","ix":3,"ks":{"a":0,"k":{"i":[[0,0],[-0.767,0.934],[0.133,1.134],[0.933,0.767],[1.2,-0.133],[0,0],[1.966,0.7],[1.966,-0.466],[1.466,-1.633],[0,-2.666],[0,0],[-1.6,-1.7],[-3.067,0],[0,0],[-1.867,0.834],[-1.1,1.267],[-0.367,1.5],[0.133,1.4],[0.633,1.1],[0.933,0.4],[1.1,-0.2],[0.9,-0.7],[0.766,-0.966],[0.766,-0.9],[0.866,-0.633],[1.133,0],[0,0],[0.466,0.367],[0,0.534],[0,0]],"o":[[1.133,-0.133],[0.766,-0.933],[-0.134,-1.2],[-0.934,-0.766],[0,0],[-1.067,-2],[-1.967,-0.7],[-1.967,0.467],[-1.467,1.634],[0,0],[0,3.2],[1.6,1.7],[0,0],[2.8,0],[1.866,-0.833],[1.1,-1.266],[0.366,-1.5],[-0.134,-1.4],[-0.634,-1.1],[-1.467,-0.6],[-1.1,0.2],[-0.9,0.7],[-0.767,0.967],[-0.767,0.9],[-0.867,0.634],[0,0],[-0.534,0],[-0.467,-0.366],[0,0],[0,0]],"v":[[73.3,-68.9],[76.15,-70.5],[77.1,-73.6],[75.5,-76.55],[72.3,-77.5],[29.1,-73.2],[24.55,-77.25],[18.65,-77.6],[13.5,-74.45],[11.3,-68],[11.3,-63.2],[13.7,-55.85],[20.7,-53.3],[76.3,-54.3],[83.3,-55.55],[87.75,-58.7],[89.95,-62.85],[90.3,-67.2],[89.15,-70.95],[86.8,-73.2],[82.95,-73.8],[79.95,-72.45],[77.45,-69.95],[75.15,-67.15],[72.7,-64.85],[69.7,-63.9],[32.4,-62.8],[30.9,-63.35],[30.2,-64.7],[30.2,-64.8]],"c":true},"ix":2},"nm":"真","mn":"ADBE Vector Shape - Group","hd":false},{"ind":3,"ty":"sh","ix":4,"ks":{"a":0,"k":{"i":[[0,0],[0,0],[0,0],[0,0]],"o":[[0,0],[0,0],[0,0],[0,0]],"v":[[50.5,-33.7],[69,-33.8],[69,-30.1],[50.5,-30]],"c":true},"ix":2},"nm":"真","mn":"ADBE Vector Shape - Group","hd":false},{"ind":4,"ty":"sh","ix":5,"ks":{"a":0,"k":{"i":[[0,0],[-0.634,-0.666],[-0.067,-0.866],[0,0],[-0.634,0.7],[-0.934,0]],"o":[[0.866,0],[0.633,0.667],[0,0],[0.066,-0.866],[0.633,-0.7],[0,0]],"v":[[65.7,-43.7],[67.95,-42.7],[69,-40.4],[50.5,-40.3],[51.55,-42.65],[53.9,-43.7]],"c":true},"ix":2},"nm":"真","mn":"ADBE Vector Shape - Group","hd":false},{"ind":5,"ty":"sh","ix":6,"ks":{"a":0,"k":{"i":[[0,0],[0.666,0.6],[0,0.934],[0,0],[0.6,-0.6],[0.866,0]],"o":[[-0.934,0],[-0.667,-0.6],[0,0],[-0.134,0.867],[-0.6,0.6],[0,0]],"v":[[53.9,-20.1],[51.5,-21],[50.5,-23.3],[69,-23.4],[67.9,-21.2],[65.7,-20.3]],"c":true},"ix":2},"nm":"真","mn":"ADBE Vector Shape - Group","hd":false}],"nm":"真","np":9,"cix":2,"bm":0,"ix":1,"mn":"ADBE Vector Group","hd":false}]}},{"ch":"题","size":100,"w":100,"data":{"shapes":[{"ty":"gr","it":[{"ind":0,"ty":"sh","ix":1,"ks":{"a":0,"k":{"i":[[0,0],[-0.8,0.867],[0.066,1.2],[0.866,0.8],[1.133,-0.066],[0,0],[0,0],[0.066,0.4],[0.134,0.4],[0,0],[-0.834,0.834],[0.066,1.2],[0.866,0.8],[1.133,-0.066],[0,0],[0.833,-0.866],[-0.067,-1.133],[-0.867,-0.833],[-1.134,0.067],[0,0],[0,-0.3],[0,-0.266],[0,0],[0,0],[0,0],[0.8,1.034],[1.333,0.2],[1,-0.8],[0.133,-1.333],[0,0],[-0.8,-1.034],[-1.334,-0.134],[-1.038,0.8],[-0.134,1.333],[0,0],[0,0],[-0.9,0.233],[-0.7,0.566],[-0.5,0.8],[-0.134,1],[1.233,1.533],[1.933,0.266],[0,0],[0,0]],"o":[[1.133,-0.066],[0.8,-0.866],[-0.067,-1.2],[-0.867,-0.8],[0,0],[0,0],[0,-0.4],[-0.067,-0.4],[0,0],[1.133,-0.066],[0.833,-0.833],[-0.067,-1.2],[-0.867,-0.8],[0,0],[-1.2,0.067],[-0.834,0.867],[0.066,1.134],[0.866,0.834],[0,0],[-0.067,0.334],[0,0.3],[0,0],[0,0],[0,0],[0.2,-1.266],[-0.8,-1.033],[-1.334,-0.133],[-1,0.8],[0,0],[-0.2,1.266],[0.8,1.033],[1.27,0.2],[1.036,-0.8],[0,0],[0,0],[1,0.133],[0.9,-0.234],[0.7,-0.567],[0.5,-0.8],[0.266,-1.934],[-1.234,-1.534],[0,0],[0,0],[0,0]],"v":[[42.6,-12.6],[45.5,-14],[46.6,-17.1],[45.2,-20.1],[42.2,-21.2],[38.2,-21],[38.2,-25.1],[38.1,-26.3],[37.798,-27.5],[43.598,-27.7],[46.548,-29.05],[47.698,-32.1],[46.298,-35.1],[43.298,-36.2],[9,-35.1],[5.95,-33.7],[4.8,-30.7],[6.2,-27.75],[9.2,-26.6],[19.3,-26.9],[19.2,-25.95],[19.2,-25.1],[19.2,-8.4],[15.4,-8.9],[16.5,-17.6],[15.6,-21.05],[12.4,-22.9],[8.9,-21.9],[7.2,-18.7],[3.5,10.6],[4.4,14.05],[7.602,15.8],[11.063,14.9],[12.819,11.7],[13.62,5.1],[88.5,15],[91.35,14.85],[93.75,13.65],[95.55,11.6],[96.5,8.9],[95.05,3.7],[90.3,1],[38.2,-6],[38.2,-12.4]],"c":true},"ix":2},"nm":"题","mn":"ADBE Vector Shape - Group","hd":false},{"ind":1,"ty":"sh","ix":2,"ks":{"a":0,"k":{"i":[[0,0],[-1.7,1.634],[0,2.334],[0,0],[0.466,1.034],[0.766,0.767],[1.033,0.434],[1.2,0],[0,0],[0,0],[0,0],[-0.767,0.8],[0.066,1.134],[0.766,0.767],[1.133,0],[0,0],[0.766,-0.8],[0,-1.133],[-0.8,-0.766],[-1.067,0.067],[0,0],[0,0],[0,0],[1.033,-0.466],[0.766,-0.766],[0.433,-1],[0,-1.2],[0,0],[-0.434,-1.033],[-0.767,-0.766],[-1.034,-0.433],[-1.134,0]],"o":[[2.333,-0.066],[1.7,-1.633],[0,0],[0,-1.133],[-0.467,-1.033],[-0.767,-0.766],[-1.034,-0.433],[0,0],[0,0],[0,0],[1.133,0],[0.766,-0.8],[0,-1.133],[-0.767,-0.766],[0,0],[-1.134,0],[-0.767,0.8],[0,1.134],[0.8,0.767],[0,0],[0,0],[0,0],[-1.134,0],[-1.034,0.467],[-0.767,0.767],[-0.434,1],[0,0],[0,1.2],[0.433,1.034],[0.766,0.767],[1.033,0.434],[0,0]],"v":[[84.4,-21.1],[90.45,-23.65],[93,-29.6],[93,-53.5],[92.3,-56.75],[90.45,-59.45],[87.75,-61.25],[84.4,-61.9],[79.3,-61.7],[79.9,-66],[90.5,-66.2],[93.35,-67.4],[94.4,-70.3],[93.25,-73.15],[90.4,-74.3],[51.5,-73.5],[48.65,-72.3],[47.5,-69.4],[48.7,-66.55],[51.5,-65.5],[62.9,-65.7],[62.4,-61.3],[57.7,-61.2],[54.45,-60.5],[51.75,-58.65],[49.95,-56],[49.3,-52.7],[49.3,-29.1],[49.95,-25.75],[51.75,-23.05],[54.45,-21.25],[57.7,-20.6]],"c":true},"ix":2},"nm":"题","mn":"ADBE Vector Shape - Group","hd":false},{"ind":2,"ty":"sh","ix":3,"ks":{"a":0,"k":{"i":[[0,0],[-1.2,0.5],[-0.934,0.9],[-0.534,1.234],[0,1.4],[0,0],[0.533,1.234],[0.933,0.9],[1.2,0.534],[1.4,0],[0,0],[1.933,-1.9],[0,-2.8],[0,0],[-0.534,-1.2],[-0.9,-0.933],[-1.2,-0.533],[-1.4,0]],"o":[[1.4,0],[1.2,-0.5],[0.933,-0.9],[0.533,-1.233],[0,0],[0,-1.4],[-0.534,-1.233],[-0.934,-0.9],[-1.2,-0.533],[0,0],[-2.8,0.067],[-1.934,1.9],[0,0],[0,1.4],[0.533,1.2],[0.9,0.934],[1.2,0.534],[0,0]],"v":[[35.6,-40],[39.5,-40.75],[42.7,-42.85],[44.9,-46.05],[45.7,-50],[45.7,-66.2],[44.9,-70.15],[42.7,-73.35],[39.5,-75.5],[35.6,-76.3],[16.8,-75.9],[9.7,-72.95],[6.8,-65.9],[6.8,-49.7],[7.6,-45.8],[9.75,-42.6],[12.9,-40.4],[16.8,-39.6]],"c":true},"ix":2},"nm":"题","mn":"ADBE Vector Shape - Group","hd":false},{"ind":3,"ty":"sh","ix":4,"ks":{"a":0,"k":{"i":[[0,0],[-0.634,1.367],[0.366,1.2],[1.166,0.767],[1.666,-0.333],[0,0],[0.466,-1.533],[-0.467,-1.533],[-1.267,-1],[-1.734,0.734]],"o":[[1.866,-0.8],[0.633,-1.366],[-0.367,-1.2],[-1.167,-0.766],[0,0],[-1.734,0.334],[-0.467,1.534],[0.466,1.534],[1.266,1],[0,0]],"v":[[64.4,-8.8],[68.15,-12.05],[68.55,-15.9],[66.25,-18.85],[62,-19.5],[52.4,-17.1],[49.1,-14.3],[49.1,-9.7],[51.7,-5.9],[56.2,-5.5]],"c":true},"ix":2},"nm":"题","mn":"ADBE Vector Shape - Group","hd":false},{"ind":4,"ty":"sh","ix":5,"ks":{"a":0,"k":{"i":[[0,0],[-1.267,1],[-0.467,1.534],[0.466,1.534],[1.733,0.334],[0,0],[1.166,-0.7],[0.366,-1.133],[-0.6,-1.3],[-1.934,-0.8]],"o":[[1.733,0.734],[1.266,-1],[0.466,-1.533],[-0.467,-1.533],[0,0],[-1.667,-0.333],[-1.167,0.7],[-0.367,1.134],[0.6,1.3],[0,0]],"v":[[87.3,-5.5],[91.8,-5.9],[94.4,-9.7],[94.4,-14.3],[91.1,-17.1],[81.5,-18.9],[77.25,-18.35],[74.95,-15.6],[75.3,-11.95],[79.1,-8.8]],"c":true},"ix":2},"nm":"题","mn":"ADBE Vector Shape - Group","hd":false},{"ind":5,"ty":"sh","ix":6,"ks":{"a":0,"k":{"i":[[0,0],[0,0],[0,0],[0,0]],"o":[[0,0],[0,0],[0,0],[0,0]],"v":[[64.9,-42.9],[77.2,-43.1],[77.2,-38.6],[64.9,-38.4]],"c":true},"ix":2},"nm":"题","mn":"ADBE Vector Shape - Group","hd":false},{"ind":6,"ty":"sh","ix":7,"ks":{"a":0,"k":{"i":[[0,0],[-0.6,0.534],[-0.734,0],[0,0],[-0.534,-0.566],[0,-0.8],[0,0],[0,0]],"o":[[0,-0.733],[0.6,-0.533],[0,0],[0.866,-0.066],[0.533,0.567],[0,0],[0,0],[0,0]],"v":[[64.9,-51.4],[65.8,-53.3],[67.8,-54.1],[74.3,-54.5],[76.4,-53.75],[77.2,-51.7],[77.2,-49.7],[64.9,-49.5]],"c":true},"ix":2},"nm":"题","mn":"ADBE Vector Shape - Group","hd":false},{"ind":7,"ty":"sh","ix":8,"ks":{"a":0,"k":{"i":[[0,0],[0.666,-0.633],[0.933,0],[0,0],[0.633,0.667],[0,0.934],[0,0],[0,0]],"o":[[0,0.934],[-0.667,0.634],[0,0],[-0.934,0.067],[-0.634,-0.666],[0,0],[0,0],[0,0]],"v":[[30.5,-50.6],[29.5,-48.25],[27.1,-47.3],[25.2,-47.3],[22.85,-48.2],[21.9,-50.6],[21.9,-53.6],[30.5,-53.8]],"c":true},"ix":2},"nm":"题","mn":"ADBE Vector Shape - Group","hd":false},{"ind":8,"ty":"sh","ix":9,"ks":{"a":0,"k":{"i":[[0,0],[-0.634,0.6],[-0.934,0.067],[0,0],[-0.667,-0.666],[0,-0.933],[0,0],[0,0]],"o":[[0,-0.933],[0.633,-0.6],[0,0],[0.933,-0.066],[0.666,0.667],[0,0],[0,0],[0,0]],"v":[[21.9,-65],[22.85,-67.3],[25.2,-68.3],[27.1,-68.3],[29.5,-67.4],[30.5,-65],[30.5,-62.3],[21.9,-62.1]],"c":true},"ix":2},"nm":"题","mn":"ADBE Vector Shape - Group","hd":false},{"ind":9,"ty":"sh","ix":10,"ks":{"a":0,"k":{"i":[[0,0],[0.533,-0.566],[0.866,0],[0,0],[0.6,0.6],[0,0.734],[0,0],[0,0]],"o":[[0,0.734],[-0.534,0.567],[0,0],[-0.734,0.067],[-0.6,-0.6],[0,0],[0,0],[0,0]],"v":[[77.2,-30.6],[76.4,-28.65],[74.3,-27.8],[67.8,-27.6],[65.8,-28.4],[64.9,-30.4],[64.9,-31.7],[77.2,-31.9]],"c":true},"ix":2},"nm":"题","mn":"ADBE Vector Shape - Group","hd":false}],"nm":"题","np":13,"cix":2,"bm":0,"ix":1,"mn":"ADBE Vector Group","hd":false}]}},{"ch":"阅","size":100,"w":100,"data":{"shapes":[{"ty":"gr","it":[{"ind":0,"ty":"sh","ix":1,"ks":{"a":0,"k":{"i":[[0,0],[0.666,-1.066],[-0.034,-1.266],[-0.834,-1.033],[-1.6,0.067],[0,0],[-0.9,-0.833],[0,-1.2],[0,0],[0.766,-0.9],[0.8,-0.7],[0.4,-0.834],[-0.8,-1.6],[-1.434,-0.767],[-1.767,-0.134],[-1.9,0.466],[-1.534,1.1],[-1,1.733],[0,2.4],[0,0],[0.733,1.667],[1.233,1.234],[1.633,0.667],[1.866,-0.133]],"o":[[-1.334,0.067],[-0.667,1.067],[0.033,1.267],[0.833,1.034],[0,0],[1.133,0],[0.9,0.834],[0,0],[0,1.734],[-0.767,0.9],[-0.8,0.7],[-0.4,0.833],[0.666,1.4],[1.433,0.766],[1.766,0.133],[1.9,-0.467],[1.533,-1.1],[1,-1.734],[0,0],[0,-1.8],[-0.734,-1.666],[-1.234,-1.233],[-1.634,-0.666],[0,0]],"v":[[41.7,-67.8],[38.7,-66.1],[37.75,-62.6],[39.05,-59.15],[42.7,-57.7],[70.4,-58.3],[73.45,-57.05],[74.8,-54],[74.8,-5.7],[73.65,-1.75],[71.3,0.65],[69.5,2.95],[70.1,6.6],[73.25,9.85],[78.05,11.2],[83.55,10.7],[88.7,8.35],[92.5,4.1],[94,-2.1],[94,-55.4],[92.9,-60.6],[89.95,-64.95],[85.65,-67.8],[80.4,-68.6]],"c":true},"ix":2},"nm":"阅","mn":"ADBE Vector Shape - Group","hd":false},{"ind":1,"ty":"sh","ix":2,"ks":{"a":0,"k":{"i":[[0,0],[0,0],[1.8,0],[0,0],[1.6,-0.533],[0,0.067],[0,0],[0.6,1.2],[1.166,0.5],[1.333,-0.4],[0.666,-1.666],[0,0],[-0.167,-0.866],[-0.534,-0.6],[-0.834,-0.3],[-0.8,0.067],[0,-1.733],[0,0],[-0.267,-0.766],[-0.534,-0.733],[0,0],[0,0],[-0.067,-1],[-0.434,-0.866],[-0.734,-0.667],[-1,-0.334],[-1,0.066],[-0.867,0.4],[-0.667,0.733],[-0.334,1],[0,0],[-0.067,0.334],[0,0.334],[0,0],[0,0],[-1.567,-1.566],[-2.534,0],[0,0],[-1.267,1.566],[-0.4,1.9],[0.566,1.6],[1.466,0.134],[0.433,-0.666],[0.133,-0.833],[0.166,-0.766],[0.866,-0.066],[0,0],[-0.867,1.167],[0,1.734],[0,0],[0.266,0.8],[0.466,0.667],[-0.867,0.334],[-0.6,0.667],[-0.234,0.934],[0.4,1.067],[0,0],[1.1,0.767],[1.4,-0.066],[0,0],[0.5,-0.8],[-0.034,-0.966],[-0.534,-0.8],[-1,0],[0,0],[-0.734,-0.5],[-0.4,-0.733]],"o":[[0,0],[-1.534,-0.6],[0,0],[-1.467,0],[0.066,0],[0,0],[0.666,-1.6],[-0.6,-1.2],[-1.167,-0.5],[-1.334,0.4],[0,0],[-0.4,1.067],[0.166,0.867],[0.533,0.6],[0.833,0.3],[-0.867,1.2],[0,0],[0,1],[0.266,0.767],[0,0],[0,0],[-0.334,1],[0.066,1],[0.433,0.866],[0.733,0.666],[1,0.333],[1,-0.067],[0.866,-0.4],[0.666,-0.734],[0,0],[0.133,-0.333],[0.066,-0.333],[0,0],[0,0],[0,2.534],[1.566,1.566],[0,0],[2.066,0],[1.266,-1.567],[0.4,-1.9],[-0.567,-1.6],[-1.4,-0.133],[-0.434,0.667],[-0.134,0.834],[-0.167,0.767],[0,0],[1.4,-0.666],[0.866,-1.166],[0,0],[0,-0.933],[-0.267,-0.8],[0.866,0.134],[0.866,-0.333],[0.6,-0.666],[0.233,-0.933],[0,0],[-0.667,-1.266],[-1.1,-0.766],[0,0],[-1,0],[-0.5,0.8],[0.033,0.967],[0.533,0.8],[0,0],[0.866,0],[0.733,0.5],[0,0]],"v":[[61.9,-37.8],[62.3,-36.4],[57.3,-37.3],[40.6,-37],[36,-36.2],[36.1,-36.3],[38.2,-40.3],[38.3,-44.5],[35.65,-47.05],[31.9,-47.2],[28.9,-44.1],[26.8,-40.1],[26.45,-37.2],[27.5,-35],[29.55,-33.65],[32,-33.3],[30.7,-28.9],[30.7,-22.1],[31.1,-19.45],[32.3,-17.2],[32.2,-17],[28.1,-5.2],[27.7,-2.2],[28.45,0.6],[30.2,2.9],[32.8,4.4],[35.8,4.8],[38.6,4.1],[40.9,2.4],[42.4,-0.2],[46.5,-11.9],[46.8,-12.9],[46.9,-13.9],[50,-14],[50,-4.6],[52.35,1.55],[58.5,3.9],[64.2,4],[69.2,1.65],[71.7,-3.55],[71.45,-8.8],[68.4,-11.4],[65.65,-10.6],[64.8,-8.35],[64.35,-5.95],[62.8,-4.7],[62.8,-15.1],[66.2,-17.85],[67.5,-22.2],[67.5,-29.2],[67.1,-31.8],[66,-34],[68.6,-34.3],[70.8,-35.8],[72.05,-38.2],[71.8,-41.2],[67.7,-49.4],[65.05,-52.45],[61.3,-53.5],[41.1,-53.1],[38.85,-51.9],[38.15,-49.25],[39,-46.6],[41.3,-45.4],[55.2,-45.6],[57.6,-44.85],[59.3,-43]],"c":true},"ix":2},"nm":"阅","mn":"ADBE Vector Shape - Group","hd":false},{"ind":2,"ty":"sh","ix":3,"ks":{"a":0,"k":{"i":[[0,0],[-0.5,-1.134],[-0.867,-0.867],[-1.134,-0.5],[-1.334,0],[-1.167,0.5],[-0.867,0.866],[-0.5,1.133],[0,1.333],[0,0],[0.5,1.167],[0.866,0.867],[1.166,0.5],[1.266,0],[1.133,-0.5],[0.866,-0.866],[0.5,-1.166],[0,-1.266]],"o":[[0,1.333],[0.5,1.133],[0.866,0.866],[1.133,0.5],[1.266,0],[1.166,-0.5],[0.866,-0.867],[0.5,-1.134],[0,0],[0,-1.266],[-0.5,-1.166],[-0.867,-0.866],[-1.167,-0.5],[-1.334,0],[-1.134,0.5],[-0.867,0.867],[-0.5,1.167],[0,0]],"v":[[5.9,2],[6.65,5.7],[8.7,8.7],[11.7,10.75],[15.4,11.5],[19.05,10.75],[22.1,8.7],[24.15,5.7],[24.9,2],[24.9,-46.1],[24.15,-49.75],[22.1,-52.8],[19.05,-54.85],[15.4,-55.6],[11.7,-54.85],[8.7,-52.8],[6.65,-49.75],[5.9,-46.1]],"c":true},"ix":2},"nm":"阅","mn":"ADBE Vector Shape - Group","hd":false},{"ind":3,"ty":"sh","ix":4,"ks":{"a":0,"k":{"i":[[-0.967,-1.733],[-1.3,-0.766],[-1.334,0.334],[-0.8,1.6],[0,0],[0.5,1.367],[1.1,1],[1.5,0.567],[1.3,-0.266],[0.866,-1.2],[-0.067,-2.4]],"o":[[0.966,1.734],[1.3,0.767],[1.333,-0.333],[0,0],[0.666,-1.333],[-0.5,-1.366],[-1.1,-1],[-1.5,-0.566],[-1.3,0.267],[-0.867,1.2],[0.133,2.534]],"v":[[20.75,-60.1],[24.15,-56.35],[28.1,-55.7],[31.3,-58.6],[33.8,-63.7],[34.05,-67.75],[31.65,-71.3],[27.75,-73.65],[23.55,-74.1],[20.3,-71.9],[19.1,-66.5]],"c":true},"ix":2},"nm":"阅","mn":"ADBE Vector Shape - Group","hd":false},{"ind":4,"ty":"sh","ix":5,"ks":{"a":0,"k":{"i":[[0,0],[0.533,-0.533],[0.8,0],[0,0],[0.5,0.5],[0,0.734],[0,0],[-0.5,0.534],[-0.734,0],[0,0],[-0.534,-0.533],[0,-0.733]],"o":[[0,0.734],[-0.534,0.534],[0,0],[-0.734,0],[-0.5,-0.5],[0,0],[0,-0.733],[0.5,-0.533],[0,0],[0.8,0],[0.533,0.534],[0,0]],"v":[[53.7,-22.8],[52.9,-20.9],[50.9,-20.1],[47.2,-20.1],[45.35,-20.85],[44.6,-22.7],[44.6,-28],[45.35,-29.9],[47.2,-30.7],[50.9,-30.7],[52.9,-29.9],[53.7,-28]],"c":true},"ix":2},"nm":"阅","mn":"ADBE Vector Shape - Group","hd":false}],"nm":"阅","np":8,"cix":2,"bm":0,"ix":1,"mn":"ADBE Vector Group","hd":false}]}},{"ch":"读","size":100,"w":100,"data":{"shapes":[{"ty":"gr","it":[{"ind":0,"ty":"sh","ix":1,"ks":{"a":0,"k":{"i":[[0,0],[0,0],[0.8,-0.844],[-0.067,-1.214],[-0.834,-0.809],[-1.2,0.067],[0,0],[0,0],[0,0],[0.833,-0.866],[-0.067,-1.133],[-0.834,-0.833],[-1.2,0.067],[0,0],[0,0],[-0.534,-1.2],[-1.034,-0.766],[-1.367,-0.266],[-1.3,0.267],[-1.067,0.934],[-0.4,1.6],[0,0],[1.4,1.567],[2.666,-0.066],[0,0],[0,0],[0,0],[-0.8,0.878],[0.066,1.214],[0.866,0.808],[1.133,0],[0,0],[0,0],[1,1.5],[1.5,0.734],[1.766,0],[1.5,-0.733],[1,-1.5],[0,-2.2]],"o":[[0,0],[-1.134,0.069],[-0.8,0.844],[0,1.147],[0.833,0.809],[0,0],[0,0],[0,0],[-1.134,0],[-0.834,0.867],[0,1.2],[0.833,0.834],[0,0],[0,0],[-0.4,1.534],[0.533,1.2],[1.033,0.767],[1.366,0.267],[1.3,-0.266],[1.066,-0.933],[0,0],[0.666,-2.866],[-1.4,-1.566],[0,0],[0,0],[0,0],[1.133,0],[0.8,-0.877],[0,-1.147],[-0.867,-0.808],[0,0],[0,0],[0,-2.2],[-1,-1.5],[-1.5,-0.733],[-1.767,0],[-1.5,0.734],[-1,1.5],[0,0]],"v":[[53.2,-65.7],[40.2,-65.4],[37.3,-64.033],[36.2,-60.947],[37.45,-58.014],[40.5,-56.9],[53.2,-57.1],[53.2,-48.7],[37.6,-48.4],[34.65,-47.1],[33.5,-44.1],[34.75,-41.05],[37.8,-39.9],[79.6,-40.9],[78.2,-35.3],[78.4,-31.2],[80.75,-28.25],[84.35,-26.7],[88.35,-26.7],[91.9,-28.5],[94.1,-32.3],[96.1,-40.5],[95,-47.15],[88.9,-49.4],[73.5,-49.2],[73.5,-57.5],[88.8,-57.905],[91.7,-59.22],[92.8,-62.356],[91.5,-65.288],[88.5,-66.5],[73.5,-66.1],[73.5,-67.3],[72,-72.85],[68.25,-76.2],[63.35,-77.3],[58.45,-76.2],[54.7,-72.85],[53.2,-67.3]],"c":true},"ix":2},"nm":"读","mn":"ADBE Vector Shape - Group","hd":false},{"ind":1,"ty":"sh","ix":2,"ks":{"a":0,"k":{"i":[[0,0],[0,0],[0.8,-0.833],[-0.067,-1.2],[-0.8,-0.8],[-1.134,0],[0,0],[0,0],[0.466,-1.134],[0,-1.234],[-0.434,-1.2],[-0.8,-1],[-1.134,-0.534],[-1.234,-0.034],[-1.234,0.366],[-1,0.8],[0,0],[-0.534,0.7],[-0.267,0.867],[0,0],[-0.8,0.834],[0.066,1.2],[0.833,0.834],[1.133,0],[0,0],[0,0],[0.533,1.167],[0.9,0.867],[1.2,0.5],[1.266,0],[1.166,-0.5],[0.9,-0.866],[0.533,-1.166],[0,-1.266]],"o":[[0,0],[-1.2,0.067],[-0.8,0.834],[0,1.134],[0.8,0.8],[0,0],[0,0],[-1,0.733],[-0.467,1.133],[0,1.233],[0.433,1.2],[0.866,1],[1.133,0.533],[1.233,0.033],[1.233,-0.367],[0,0],[0.666,-0.533],[0.533,-0.7],[0,0],[1.133,-0.066],[0.8,-0.833],[0,-1.133],[-0.834,-0.833],[0,0],[0,0],[0,-1.266],[-0.534,-1.166],[-0.9,-0.866],[-1.2,-0.5],[-1.267,0],[-1.167,0.5],[-0.9,0.867],[-0.534,1.167],[0,0]],"v":[[56.7,-18.2],[35.3,-17.8],[32.3,-16.45],[31.2,-13.4],[32.4,-10.5],[35.3,-9.3],[47.1,-9.4],[36.7,-0.6],[34.5,2.2],[33.8,5.75],[34.45,9.4],[36.3,12.7],[39.3,15],[42.85,15.85],[46.55,15.35],[49.9,13.6],[72.5,-5.7],[74.3,-7.55],[75.5,-9.9],[92.9,-10.3],[95.8,-11.65],[96.9,-14.7],[95.65,-17.65],[92.7,-18.9],[76.2,-18.6],[76.2,-29],[75.4,-32.65],[73.25,-35.7],[70.1,-37.75],[66.4,-38.5],[62.75,-37.75],[59.65,-35.7],[57.5,-32.65],[56.7,-29]],"c":true},"ix":2},"nm":"读","mn":"ADBE Vector Shape - Group","hd":false},{"ind":2,"ty":"sh","ix":3,"ks":{"a":0,"k":{"i":[[-0.334,-0.366],[0,-0.533],[0,0],[-1.034,-1.4],[-1.634,-0.667],[-1.9,0],[-1.734,0.566],[-1.267,1],[-0.4,1.333],[0.333,0.5],[0.566,0.3],[0.533,0.5],[0,1.534],[0,0],[7.4,-0.333],[0,0],[0.8,-0.866],[-0.134,-1.2],[-0.767,-0.766],[-1.067,-0.066]],"o":[[0.333,0.367],[0,0],[0,2.266],[1.033,1.4],[1.633,0.666],[1.9,0],[1.733,-0.567],[1.266,-1],[0.4,-1.467],[-0.334,-0.5],[-0.567,-0.3],[-0.534,-0.5],[0,0],[0,-7.666],[0,0],[-1.134,0.067],[-0.8,0.867],[0,1.067],[0.766,0.767],[0.533,0]],"v":[[8.2,-35.45],[8.7,-34.1],[8.7,-0.8],[10.25,4.7],[14.25,7.8],[19.55,8.8],[25,7.95],[29.5,5.6],[32,2.1],[32.1,-0.85],[30.75,-2.05],[29.1,-3.25],[28.3,-6.3],[28.3,-34],[17.2,-45],[6.9,-44.5],[4,-43.1],[3,-40],[4.15,-37.25],[6.9,-36]],"c":true},"ix":2},"nm":"读","mn":"ADBE Vector Shape - Group","hd":false},{"ind":3,"ty":"sh","ix":4,"ks":{"a":0,"k":{"i":[[0,0],[-1.434,-0.167],[-1.234,0.633],[-0.934,1.3],[-0.3,1.433],[0.433,1.433],[1.533,0.933],[0,0],[1.6,-0.333],[1.033,-1.133],[0.066,-1.733],[-1.6,-1.934]],"o":[[1.266,1.466],[1.433,0.166],[1.233,-0.634],[0.933,-1.3],[0.3,-1.434],[-0.434,-1.434],[0,0],[-1.4,-0.866],[-1.6,0.334],[-1.034,1.134],[-0.067,1.733],[0,0]],"v":[[81.1,13],[85.15,15.45],[89.15,14.75],[92.4,11.85],[94.25,7.75],[94.05,3.45],[91.1,-0.1],[82.7,-5.4],[78.2,-6.2],[74.25,-4],[72.6,0.3],[74.9,5.8]],"c":true},"ix":2},"nm":"读","mn":"ADBE Vector Shape - Group","hd":false},{"ind":4,"ty":"sh","ix":5,"ks":{"a":0,"k":{"i":[[-1.034,-1.8],[-1.334,-0.8],[-1.4,0.334],[-0.867,1.667],[0,0],[0.533,1.367],[1.166,1.034],[1.566,0.567],[1.366,-0.233],[0.933,-1.233],[-0.134,-2.466]],"o":[[1.033,1.8],[1.333,0.8],[1.4,-0.333],[0,0],[0.733,-1.4],[-0.534,-1.366],[-1.167,-1.033],[-1.567,-0.566],[-1.367,0.234],[-0.934,1.234],[0.066,2.6]],"v":[[12.05,-55],[15.6,-51.1],[19.7,-50.4],[23.1,-53.4],[25.8,-58.7],[26.1,-62.85],[23.55,-66.45],[19.45,-68.85],[15.05,-69.35],[11.6,-67.15],[10.4,-61.6]],"c":true},"ix":2},"nm":"读","mn":"ADBE Vector Shape - Group","hd":false},{"ind":5,"ty":"sh","ix":6,"ks":{"a":0,"k":{"i":[[-0.734,-0.933],[-0.934,-0.466],[-1.034,0.2],[-0.734,1.134],[0,0],[0.333,0.8],[0.866,0.534],[1.166,0.2],[1,-0.233],[0.666,-0.733],[-0.2,-1.266]],"o":[[0.733,0.934],[0.933,0.467],[1.033,-0.2],[0,0],[0.6,-0.933],[-0.334,-0.8],[-0.867,-0.533],[-1.167,-0.2],[-1,0.234],[-0.667,0.734],[0.133,1.134]],"v":[[45.4,-30.8],[47.9,-28.7],[50.85,-28.3],[53.5,-30.3],[55,-32.7],[55.4,-35.3],[53.6,-37.3],[50.55,-38.4],[47.3,-38.35],[44.8,-36.9],[44.1,-33.9]],"c":true},"ix":2},"nm":"读","mn":"ADBE Vector Shape - Group","hd":false},{"ind":6,"ty":"sh","ix":7,"ks":{"a":0,"k":{"i":[[-0.667,-0.966],[-0.834,-0.466],[-0.934,0.2],[-0.667,1.2],[0,0],[0.333,0.8],[0.8,0.5],[1.066,0.2],[0.933,-0.266],[0.6,-0.733],[-0.2,-1.266]],"o":[[0.666,0.967],[0.833,0.467],[0.933,-0.2],[0,0],[0.6,-0.933],[-0.334,-0.8],[-0.8,-0.5],[-1.067,-0.2],[-0.934,0.267],[-0.6,0.734],[0.133,1.067]],"v":[[37.1,-21.95],[39.35,-19.8],[42,-19.4],[44.4,-21.5],[45.9,-24],[46.3,-26.6],[44.6,-28.55],[41.8,-29.6],[38.8,-29.5],[36.5,-28],[35.9,-25]],"c":true},"ix":2},"nm":"读","mn":"ADBE Vector Shape - Group","hd":false}],"nm":"读","np":10,"cix":2,"bm":0,"ix":1,"mn":"ADBE Vector Group","hd":false}]}}]}